dilithium/__init__.py
dilithium/aes256_ctr_drbg.py
dilithium/benchmark_dilithium.py
dilithium/dilithium.py
dilithium/modules.py
dilithium/ntt_helper.py
dilithium/polynomials.py
dilithium/shake_wrapper.py
dilithium/test_dilithium.py
dilithium/utils.py
dilithium/xoshiro128starstar.py
dilithium-1.0.6.dist-info/LICENSE
dilithium-1.0.6.dist-info/METADATA
dilithium-1.0.6.dist-info/WHEEL
dilithium-1.0.6.dist-info/top_level.txt
dilithium-1.0.6.dist-info/RECORD
