Metadata-Version: 2.1
Name: dilithium
Version: 1.0.6
Summary: CRYSTALS-Dilithium for eShard
Home-page: https://eshard.com
Author: eshard
License: MIT
Keywords: PQC,Digital-Signatures,Dilithium
Classifier: Programming Language :: Python :: 3
Classifier: Development Status :: 4 - Beta
Classifier: Intended Audience :: Developers
Classifier: License :: OSI Approved :: GNU General Public License v3 (GPLv3)
License-File: LICENSE
Requires-Dist: pycryptodome (>=03.14.1)
